LICENSE
README.md
setup.py
bann_flow/__init__ .py
bann_flow/__version__.py
bann_flow/bb.py
bann_flow/data.py
bann_flow/f.py
bann_flow/loss.py
bann_flow/m.py
bann_flow/utils.py
bann_flow.egg-info/PKG-INFO
bann_flow.egg-info/SOURCES.txt
bann_flow.egg-info/dependency_links.txt
bann_flow.egg-info/requires.txt
bann_flow.egg-info/top_level.txt
bann_flow/paper/__init__.py
bann_flow/paper/bb.py